CHANGES
LICENSE
MANIFEST.in
README.md
longdesc.rst
requirements.txt
setup.py
kaplot/__init__.py
kaplot/defaults.py
kaplot.egg-info/PKG-INFO
kaplot.egg-info/SOURCES.txt
kaplot.egg-info/dependency_links.txt
kaplot.egg-info/requires.txt
kaplot.egg-info/top_level.txt
kaplot_backend/__init__.py