Metadata-Version: 1.1
Name: kaplot
Version: 1.0.0-beta6
Summary: A plotting tool built around/on matplotlib
Home-page: http://github.com/kamilm/kaplot
Author: Kamil Mielczarek
Author-email: kamil.m@gmail.com
License: UNKNOWN
Platform: UNKNOWN
Classifier: Development Status :: 4 - Beta
Classifier: Intended Audience :: Science/Research
Classifier: Topic :: Scientific/Engineering :: Visualization
Classifier: Programming Language :: Python :: 2.6
Classifier: Programming Language :: Python :: 2.7
Classifier: Operating System :: OS Independent
Classifier: License :: OSI Approved :: MIT License
